second_brain_tools/.sbt_config
second_brain_tools/__init__.py
second_brain_tools/__main__.py
second_brain_tools/append.py
second_brain_tools/capture.py
second_brain_tools/cli.py
second_brain_tools/config.py
second_brain_tools/daily_note.py
second_brain_tools/defaults.py
second_brain_tools/directories.py
second_brain_tools/misc.py
second_brain_tools/notes.py
second_brain_tools/quick_capture.py
second_brain_tools/routines.py
second_brain_tools/setup.py
second_brain_tools/time.py
second_brain_tools/url.py
second_brain_tools-0.0.3.dist-info/AUTHORS.rst
second_brain_tools-0.0.3.dist-info/LICENSE
second_brain_tools-0.0.3.dist-info/METADATA
second_brain_tools-0.0.3.dist-info/WHEEL
second_brain_tools-0.0.3.dist-info/entry_points.txt
second_brain_tools-0.0.3.dist-info/top_level.txt
second_brain_tools-0.0.3.dist-info/RECORD
