Metadata-Version: 2.1
Name: second-brain-tools
Version: 0.0.3
Summary: This project is a toolset for Second Brain,
Home-page: https://github.com/rohanbatrain/Second-Brain-Tools
Author: Rohan Batra
Author-email: me@rohanbatra.in
License: Apache-2.0
Project-URL: Changelog, https://github.com/rohanbatrain/Second-Brain-Tools/blob/master/CHANGELOG.rst
Project-URL: Issue Tracker, https://github.com/rohanbatrain/Second-Brain-Tools/issues
Classifier: Development Status :: 1 - Planning
Classifier: Intended Audience :: Developers
Classifier: License :: OSI Approved :: Apache Software License
Classifier: Operating System :: Unix
Classifier: Operating System :: POSIX
Classifier: Operating System :: Microsoft :: Windows
Classifier: Programming Language :: Python
Classifier: Programming Language :: Python :: 3
Classifier: Programming Language :: Python :: 3 :: Only
Classifier: Programming Language :: Python :: 3.7
Classifier: Programming Language :: Python :: 3.8
Classifier: Programming Language :: Python :: 3.9
Classifier: Programming Language :: Python :: 3.10
Classifier: Programming Language :: Python :: 3.11
Classifier: Programming Language :: Python :: Implementation :: CPython
Classifier: Programming Language :: Python :: Implementation :: PyPy
Classifier: Topic :: Utilities
Requires-Python: >=3.7
License-File: LICENSE
License-File: AUTHORS.rst
Requires-Dist: python-dotenv
Requires-Dist: rich
Requires-Dist: typer
Requires-Dist: click
Requires-Dist: gitpython
